auto_impl/__init__.py
auto_impl-0.1.3.dist-info/LICENSE
auto_impl-0.1.3.dist-info/METADATA
auto_impl-0.1.3.dist-info/WHEEL
auto_impl-0.1.3.dist-info/top_level.txt
auto_impl-0.1.3.dist-info/RECORD
