Metadata-Version: 2.1
Name: auto_impl
Version: 0.1.3
Summary: Automatically implements functions using ChatGPT.
Author-email: "Harry T. Ma" <harrymaofshs@gmail.com>
License: MIT License
Project-URL: Homepage, https://github.com/HarryTMa/auto_impl
Project-URL: repository, https://github.com/HarryTMa/auto_impl
Project-URL: Bug Tracker, https://github.com/HarryTMa/auto_impl/issues
Classifier: Programming Language :: Python :: 3
Classifier: Programming Language :: Python :: 3.8
Classifier: Programming Language :: Python :: 3.9
Classifier: Programming Language :: Python :: 3.10
Classifier: Programming Language :: Python :: 3.11
Classifier: Programming Language :: Python :: 3.12
Classifier: License :: OSI Approved :: MIT License
Classifier: Operating System :: OS Independent
Requires-Python: >=3.8
License-File: LICENSE
Requires-Dist: llm
